neos_client/__init__.py
neos_client/client.py
neos_client-0.0.1.dist-info/LICENSE
neos_client-0.0.1.dist-info/METADATA
neos_client-0.0.1.dist-info/WHEEL
neos_client-0.0.1.dist-info/top_level.txt
neos_client-0.0.1.dist-info/RECORD
